dbis_relational_model/__init__.py
dbis_relational_model/relational_model.py
dbis_relational_model-1.0.3.dist-info/licenses/LICENSE
dbis_relational_model-1.0.3.dist-info/METADATA
dbis_relational_model-1.0.3.dist-info/WHEEL
dbis_relational_model-1.0.3.dist-info/top_level.txt
dbis_relational_model-1.0.3.dist-info/RECORD
